tracardi_regex_validator/plugin.py
tracardi_regex_validator/model/__init__.py
tracardi_regex_validator/model/configuration.py
tracardi_regex_validator/model/__pycache__/__init__.cpython-38.pyc
tracardi_regex_validator/model/__pycache__/configuration.cpython-38.pyc
tracardi_regex_validator/service/__init__.py
tracardi_regex_validator/service/validator.py
tracardi_regex_validator/service/__pycache__/__init__.cpython-38.pyc
tracardi_regex_validator/service/__pycache__/validator.cpython-38.pyc
tracardi_regex_validator/test/test_regex_plugin.py
tracardi_regex_validator-0.6.1.dist-info/LICENSE.md
tracardi_regex_validator-0.6.1.dist-info/METADATA
tracardi_regex_validator-0.6.1.dist-info/WHEEL
tracardi_regex_validator-0.6.1.dist-info/top_level.txt
tracardi_regex_validator-0.6.1.dist-info/RECORD
